LICENSE
MANIFEST.in
README.rst
setup.py
django_talkback.egg-info/PKG-INFO
django_talkback.egg-info/SOURCES.txt
django_talkback.egg-info/dependency_links.txt
django_talkback.egg-info/requires.txt
django_talkback.egg-info/top_level.txt
talkback/__init__.py
talkback/admin.py
talkback/forms.py
talkback/middleware.py
talkback/models.py
talkback/settings.py
talkback/urls.py
talkback/views.py
talkback/migrations/0001_initial.py
talkback/migrations/__init__.py
talkback/static/talkback/script.js
talkback/static/talkback/styles.css
talkback/templates/talkback/email_notification.txt
talkback/templates/talkback/feedback_form.html
talkback/utils/__init__.py
talkback/utils/emails.py
talkback/utils/widgets.py