Metadata-Version: 1.1
Name: django-talkback
Version: 0.1.1
Summary: A pluggable app for adding an AJAX feedback form to Django-powered websites.
Home-page: http://github.com/littleweaver/django-talkback
Author: Little Weaver Web Collective, LLC
Author-email: hello@littleweaverweb.com
License: UNKNOWN
Platform: OS Independent
Classifier: Environment :: Web Environment
Classifier: Framework :: Django
Classifier: Intended Audience :: Other Audience
Classifier: License :: OSI Approved :: BSD License
Classifier: Operating System :: OS Independent
Classifier: Programming Language :: Python
Classifier: Topic :: Internet :: WWW/HTTP :: Dynamic Content
